{
  "info": {
    "name": "Instructor API Tests",
    "description": "Comprehensive test suite for Instructor API endpoints",
    "schema": "https://schema.getpostman.com/json/collection/v2.1.0/collection.json"
  },
  "item": [
    {
      "name": "Authentication",
      "item": [
        {
          "name": "Instructor Login",
          "event": [
            {
              "listen": "test",
              "script": {
                "exec": [
                  "pm.test(\"Status code is 200\", () => pm.response.to.have.status(200));",
                  "pm.test(\"Response has token\", () => {",
                  "    const json = pm.response.json();",
                  "    pm.expect(json.success).to.be.true;",
                  "    pm.expect(json.data.token).to.exist;",
                  "    pm.collectionVariables.set('instructor_token', json.data.token);",
                  "    // Set as global for this session",
                  "    pm.globals.set('instructor_token', json.data.token);",
                  "});"
                ],
                "type": "text/javascript"
              }
            }
          ],
          "request": {
            "method": "POST",
            "header": [
              {
                "key": "Content-Type",
                "value": "application/json"
              }
            ],
            "body": {
              "mode": "raw",
              "raw": "{\n  \"email\": \"instructor@medh.co\",\n  \"password\": \"Instructor@123\"\n}"
            },
            "url": "{{base_url}}/auth/login"
          }
        }
      ]
    },
    {
      "name": "Instructor Dashboard",
      "item": [
        {
          "name": "Get Instructor Courses",
          "event": [
            {
              "listen": "test",
              "script": {
                "exec": [
                  "pm.test(\"Status code is 200\", () => pm.response.to.have.status(200));",
                  "pm.test(\"Response success is true\", () => {",
                  "    const json = pm.response.json();",
                  "    pm.expect(json.success).to.be.true;",
                  "});",
                  "pm.test(\"Courses is array\", () => {",
                  "    const json = pm.response.json();",
                  "    pm.expect(json.data).to.be.an('array');",
                  "});",
                  "pm.test(\"Set course_id for further tests\", () => {",
                  "    const json = pm.response.json();",
                  "    if (json.data && json.data.length > 0) {",
                  "        pm.collectionVariables.set('course_id', json.data[0]._id);",
                  "    }",
                  "});"
                ],
                "type": "text/javascript"
              }
            }
          ],
          "request": {
            "method": "GET",
            "header": [
              {
                "key": "Authorization",
                "value": "Bearer {{instructor_token}}"
              }
            ],
            "url": "{{base_url}}/instructors/courses"
          }
        },
        {
          "name": "Get Course Students",
          "event": [
            {
              "listen": "test",
              "script": {
                "exec": [
                  "pm.test(\"Status code is 200\", () => pm.response.to.have.status(200));",
                  "pm.test(\"Response success is true\", () => {",
                  "    const json = pm.response.json();",
                  "    pm.expect(json.success).to.be.true;",
                  "});",
                  "pm.test(\"Students is array\", () => {",
                  "    const json = pm.response.json();",
                  "    pm.expect(json.data).to.be.an('array');",
                  "});",
                  "pm.test(\"Set student_id for further tests\", () => {",
                  "    const json = pm.response.json();",
                  "    if (json.data && json.data.length > 0) {",
                  "        pm.collectionVariables.set('student_id', json.data[0].student._id);",
                  "    }",
                  "});"
                ],
                "type": "text/javascript"
              }
            }
          ],
          "request": {
            "method": "GET",
            "header": [
              {
                "key": "Authorization",
                "value": "Bearer {{instructor_token}}"
              }
            ],
            "url": "{{base_url}}/instructors/students/{{course_id}}"
          }
        },
        {
          "name": "Get Instructor Dashboard Stats",
          "event": [
            {
              "listen": "test",
              "script": {
                "exec": [
                  "pm.test(\"Status code is 200\", () => pm.response.to.have.status(200));",
                  "pm.test(\"Response success is true\", () => {",
                  "    const json = pm.response.json();",
                  "    pm.expect(json.success).to.be.true;",
                  "});",
                  "pm.test(\"Stats data exists\", () => {",
                  "    const json = pm.response.json();",
                  "    pm.expect(json.data).to.exist;",
                  "});"
                ],
                "type": "text/javascript"
              }
            }
          ],
          "request": {
            "method": "GET",
            "header": [
              {
                "key": "Authorization",
                "value": "Bearer {{instructor_token}}"
              }
            ],
            "url": "{{base_url}}/instructors/dashboard/stats"
          }
        }
      ]
    },
    {
      "name": "Attendance Management",
      "item": [
        {
          "name": "Get Batch Attendance",
          "event": [
            {
              "listen": "test",
              "script": {
                "exec": [
                  "pm.test(\"Status code is 200\", () => pm.response.to.have.status(200));",
                  "pm.test(\"Response success is true\", () => {",
                  "    const json = pm.response.json();",
                  "    pm.expect(json.success).to.be.true;",
                  "});",
                  "pm.test(\"Attendance data exists\", () => {",
                  "    const json = pm.response.json();",
                  "    pm.expect(json.data).to.exist;",
                  "});"
                ],
                "type": "text/javascript"
              }
            }
          ],
          "request": {
            "method": "GET",
            "header": [
              {
                "key": "Authorization",
                "value": "Bearer {{instructor_token}}"
              }
            ],
            "url": "{{base_url}}/attendance/batch/{{batch_id}}"
          }
        },
        {
          "name": "Mark Student Attendance",
          "event": [
            {
              "listen": "test",
              "script": {
                "exec": [
                  "pm.test(\"Status code is 200 or 201\", () => {",
                  "    pm.expect([200, 201]).to.include(pm.response.code);",
                  "});",
                  "pm.test(\"Response success is true\", () => {",
                  "    const json = pm.response.json();",
                  "    pm.expect(json.success).to.be.true;",
                  "});",
                  "pm.test(\"Attendance record created\", () => {",
                  "    const json = pm.response.json();",
                  "    pm.expect(json.data).to.exist;",
                  "});"
                ],
                "type": "text/javascript"
              }
            }
          ],
          "request": {
            "method": "POST",
            "header": [
              {
                "key": "Content-Type",
                "value": "application/json"
              },
              {
                "key": "Authorization",
                "value": "Bearer {{instructor_token}}"
              }
            ],
            "body": {
              "mode": "raw",
              "raw": "{\n  \"batch_id\": \"507f1f77bcf86cd799439011\",\n  \"session_date\": \"{{$isoTimestamp}}\",\n  \"session_type\": \"live_class\",\n  \"session_title\": \"Test Session - Marking Attendance\",\n  \"session_duration_minutes\": 60,\n  \"attendance_records\": [\n    {\n      \"student_id\": \"507f1f77bcf86cd799439012\",\n      \"status\": \"present\",\n      \"join_time\": \"10:00 AM\",\n      \"leave_time\": \"11:00 AM\",\n      \"duration_minutes\": 60\n    }\n  ]\n}"
            },
            "url": "{{base_url}}/attendance/mark"
          }
        },
        {
          "name": "Update Attendance",
          "event": [
            {
              "listen": "test",
              "script": {
                "exec": [
                  "pm.test(\"Status code is 200\", () => pm.response.to.have.status(200));",
                  "pm.test(\"Response success is true\", () => {",
                  "    const json = pm.response.json();",
                  "    pm.expect(json.success).to.be.true;",
                  "});",
                  "pm.test(\"Attendance updated\", () => {",
                  "    const json = pm.response.json();",
                  "    pm.expect(json.data).to.exist;",
                  "});"
                ],
                "type": "text/javascript"
              }
            }
          ],
          "request": {
            "method": "PUT",
            "header": [
              {
                "key": "Content-Type",
                "value": "application/json"
              },
              {
                "key": "Authorization",
                "value": "Bearer {{instructor_token}}"
              }
            ],
            "body": {
              "mode": "raw",
              "raw": "{\n  \"status\": \"absent\",\n  \"notes\": \"Updated attendance status\"\n}"
            },
            "url": "{{base_url}}/attendance/{{attendance_id}}"
          }
        }
      ]
    },
    {
      "name": "Revenue Management",
      "item": [
        {
          "name": "Get Instructor Revenue Stats",
          "event": [
            {
              "listen": "test",
              "script": {
                "exec": [
                  "pm.test(\"Status code is 200\", () => pm.response.to.have.status(200));",
                  "pm.test(\"Response success is true\", () => {",
                  "    const json = pm.response.json();",
                  "    pm.expect(json.success).to.be.true;",
                  "});",
                  "pm.test(\"Revenue data exists\", () => {",
                  "    const json = pm.response.json();",
                  "    pm.expect(json.data).to.exist;",
                  "});"
                ],
                "type": "text/javascript"
              }
            }
          ],
          "request": {
            "method": "GET",
            "header": [
              {
                "key": "Authorization",
                "value": "Bearer {{instructor_token}}"
              }
            ],
            "url": "{{base_url}}/instructors/revenue/stats"
          }
        },
        {
          "name": "Get Monthly Revenue",
          "event": [
            {
              "listen": "test",
              "script": {
                "exec": [
                  "pm.test(\"Status code is 200\", () => pm.response.to.have.status(200));",
                  "pm.test(\"Response success is true\", () => {",
                  "    const json = pm.response.json();",
                  "    pm.expect(json.success).to.be.true;",
                  "});",
                  "pm.test(\"Monthly revenue data exists\", () => {",
                  "    const json = pm.response.json();",
                  "    pm.expect(json.data).to.exist;",
                  "});"
                ],
                "type": "text/javascript"
              }
            }
          ],
          "request": {
            "method": "GET",
            "header": [
              {
                "key": "Authorization",
                "value": "Bearer {{instructor_token}}"
              }
            ],
            "url": "{{base_url}}/instructors/revenue/monthly"
          }
        },
        {
          "name": "Get Revenue Details",
          "event": [
            {
              "listen": "test",
              "script": {
                "exec": [
                  "pm.test(\"Status code is 200\", () => pm.response.to.have.status(200));",
                  "pm.test(\"Response success is true\", () => {",
                  "    const json = pm.response.json();",
                  "    pm.expect(json.success).to.be.true;",
                  "});",
                  "pm.test(\"Revenue details exist\", () => {",
                  "    const json = pm.response.json();",
                  "    pm.expect(json.data).to.exist;",
                  "});"
                ],
                "type": "text/javascript"
              }
            }
          ],
          "request": {
            "method": "GET",
            "header": [
              {
                "key": "Authorization",
                "value": "Bearer {{instructor_token}}"
              }
            ],
            "url": "{{base_url}}/instructors/revenue/details?startDate=2024-01-01&endDate=2024-12-31"
          }
        }
      ]
    },
    {
      "name": "Course Management",
      "item": [
        {
          "name": "Get Course Details",
          "event": [
            {
              "listen": "test",
              "script": {
                "exec": [
                  "pm.test(\"Status code is 200\", () => pm.response.to.have.status(200));",
                  "pm.test(\"Response success is true\", () => {",
                  "    const json = pm.response.json();",
                  "    pm.expect(json.success).to.be.true;",
                  "});",
                  "pm.test(\"Course details exist\", () => {",
                  "    const json = pm.response.json();",
                  "    pm.expect(json.data).to.exist;",
                  "    pm.expect(json.data._id).to.exist;",
                  "});"
                ],
                "type": "text/javascript"
              }
            }
          ],
          "request": {
            "method": "GET",
            "header": [
              {
                "key": "Authorization",
                "value": "Bearer {{instructor_token}}"
              }
            ],
            "url": "{{base_url}}/instructors/courses/{{course_id}}"
          }
        },
        {
          "name": "Get Course Batches",
          "event": [
            {
              "listen": "test",
              "script": {
                "exec": [
                  "pm.test(\"Status code is 200\", () => pm.response.to.have.status(200));",
                  "pm.test(\"Response success is true\", () => {",
                  "    const json = pm.response.json();",
                  "    pm.expect(json.success).to.be.true;",
                  "});",
                  "pm.test(\"Batches is array\", () => {",
                  "    const json = pm.response.json();",
                  "    pm.expect(json.data).to.be.an('array');",
                  "});",
                  "pm.test(\"Set batch_id for further tests\", () => {",
                  "    const json = pm.response.json();",
                  "    if (json.data && json.data.length > 0) {",
                  "        pm.collectionVariables.set('batch_id', json.data[0]._id);",
                  "    }",
                  "});"
                ],
                "type": "text/javascript"
              }
            }
          ],
          "request": {
            "method": "GET",
            "header": [
              {
                "key": "Authorization",
                "value": "Bearer {{instructor_token}}"
              }
            ],
            "url": "{{base_url}}/instructors/courses/{{course_id}}/batches"
          }
        }
      ]
    }
  ],
  "variable": [
    {
      "key": "base_url",
      "value": "http://localhost:8080/api/v1",
      "type": "string"
    },
    {
      "key": "instructor_token",
      "value": "",
      "type": "string"
    },
    {
      "key": "course_id",
      "value": "",
      "type": "string"
    },
    {
      "key": "batch_id",
      "value": "dummy-batch-id",
      "type": "string"
    },
    {
      "key": "student_id",
      "value": "dummy-student-id",
      "type": "string"
    },
    {
      "key": "attendance_id",
      "value": "dummy-attendance-id",
      "type": "string"
    }
  ]
}